prtools/__init__.py
prtools/array.py
prtools/convolve.py
prtools/cost.py
prtools/fourier.py
prtools/jax.py
prtools/misc.py
prtools/segmented.py
prtools/shape.py
prtools/sparse.py
prtools/stats.py
prtools/zernike.py
prtools/backend/__init__.py
prtools/backend/_base.py
prtools/backend/_jax.py
prtools/backend/_numpy.py
prtools-1.4.2.dist-info/licenses/LICENSE
prtools-1.4.2.dist-info/licenses/NOTICE
prtools-1.4.2.dist-info/METADATA
prtools-1.4.2.dist-info/WHEEL
prtools-1.4.2.dist-info/top_level.txt
prtools-1.4.2.dist-info/RECORD
