Metadata-Version: 2.4
Name: prtools
Version: 1.4.2
Summary: Utility functions for image-based phase retrieval
Author: Andy Kee
License: MIT License
Project-URL: Homepage, https://github.com/andykee/prtools
Project-URL: Documentation, https://andykee.github.io/prtools/
Project-URL: Bug Tracker, https://github.com/andykee/prtools/issues
Classifier: Development Status :: 5 - Production/Stable
Classifier: Intended Audience :: Science/Research
Classifier: License :: OSI Approved :: MIT License
Classifier: Programming Language :: Python :: 3
Classifier: Topic :: Scientific/Engineering
Classifier: Topic :: Scientific/Engineering :: Astronomy
Classifier: Topic :: Scientific/Engineering :: Image Processing
Classifier: Topic :: Scientific/Engineering :: Mathematics
Classifier: Topic :: Scientific/Engineering :: Physics
Requires-Python: >=3.8
License-File: LICENSE
License-File: NOTICE
Requires-Dist: numpy
Requires-Dist: scipy
Provides-Extra: jax
Requires-Dist: jax; extra == "jax"
Requires-Dist: optax; extra == "jax"
Dynamic: license-file
